uvm/__init__.py
uvm/__main__.py
uvm/commands/__init__.py
uvm/commands/build_command.py
uvm/commands/code_command.py
uvm/commands/major_command.py
uvm/commands/minor_command.py
uvm/commands/patch_command.py
uvm/core.py
uvm/main.py
uvm/utils.py
uvm-1.0.2.dist-info/entry_points.txt
uvm-1.0.2.dist-info/LICENSE
uvm-1.0.2.dist-info/WHEEL
uvm-1.0.2.dist-info/METADATA
uvm-1.0.2.dist-info/RECORD
