Metadata-Version: 2.1
Name: uvm
Version: 1.0.2
Summary: Unity Version Manager CLI implemented with Python and Typer
Home-page: https://github.com/educup/uvm
License: MIT
Author: educup
Author-email: hello@educup.io
Requires-Python: >=3.8,<4.0
Classifier: License :: OSI Approved :: MIT License
Classifier: Programming Language :: Python :: 3
Classifier: Programming Language :: Python :: 3.8
Classifier: Programming Language :: Python :: 3.9
Requires-Dist: typer (>=0.3.2,<0.4.0)
Project-URL: Documentation, https://github.com/educup/uvm
Project-URL: Repository, https://github.com/educup/uvm
